viltolyckor/__init__.py
viltolyckor/scraper.py
viltolyckor/utils.py
viltolyckor_scraper-0.2.0.dist-info/LICENSE
viltolyckor_scraper-0.2.0.dist-info/METADATA
viltolyckor_scraper-0.2.0.dist-info/WHEEL
viltolyckor_scraper-0.2.0.dist-info/top_level.txt
viltolyckor_scraper-0.2.0.dist-info/RECORD
