Metadata-Version: 2.1
Name: viltolyckor-scraper
Version: 0.2.0
Summary: A scraper of statistical data from viltolyckor.se, built on top of Statscraper.
Home-page: https://github.com/jplusplus/viltolyckor_scraper
Author: Jens Finnäs
Author-email: jens.finnas@gmail.com
License: MIT
Download-URL: https://github.com/jplusplus/viltolyckor_scraper/archive/0.2.0.tar.gz
Platform: UNKNOWN
Requires-Dist: beautifulsoup4
Requires-Dist: lxml
Requires-Dist: requests
Requires-Dist: statscraper
